{
    "key": "group_5b6b8419b65ac",
    "title": "Data Focus Template",
    "fields": [
        {
            "key": "field_5b6b8635b5acb",
            "label": "Visualizations Title",
            "name": "title",
            "type": "text",
            "instructions": "",
            "required": 0,
            "conditional_logic": 0,
            "wrapper": {
                "width": "",
                "class": "",
                "id": ""
            },
            "default_value": "",
            "placeholder": "",
            "prepend": "",
            "append": "",
            "maxlength": ""
        },
        {
            "key": "field_5b6b84343d00a",
            "label": "Visualizations",
            "name": "visualizations",
            "type": "relationship",
            "instructions": "",
            "required": 0,
            "conditional_logic": 0,
            "wrapper": {
                "width": "",
                "class": "",
                "id": ""
            },
            "post_type": [
                "visualization"
            ],
            "taxonomy": [],
            "filters": [
                "search",
                "post_type",
                "taxonomy"
            ],
            "elements": "",
            "min": "",
            "max": "",
            "return_format": "object"
        },
        {
            "key": "field_5b6b864cb5acc",
            "label": "Enable \"Jump To Section\"",
            "name": "enable_jump_to_section",
            "type": "true_false",
            "instructions": "",
            "required": 0,
            "conditional_logic": 0,
            "wrapper": {
                "width": "",
                "class": "",
                "id": ""
            },
            "message": "",
            "default_value": 0,
            "ui": 0,
            "ui_on_text": "",
            "ui_off_text": ""
        },
        {
            "key": "field_5b6b865cb5acd",
            "label": "Enable \"Choose Year\"",
            "name": "enable_choose_year",
            "type": "text",
            "instructions": "",
            "required": 0,
            "conditional_logic": 0,
            "wrapper": {
                "width": "",
                "class": "",
                "id": ""
            },
            "default_value": "",
            "placeholder": "",
            "prepend": "",
            "append": "",
            "maxlength": ""
        }
    ],
    "location": [
        [
            {
                "param": "post_type",
                "operator": "==",
                "value": "page"
            },
            {
                "param": "post_template",
                "operator": "==",
                "value": "page-data-focus.php"
            }
        ]
    ],
    "menu_order": 0,
    "position": "normal",
    "style": "default",
    "label_placement": "top",
    "instruction_placement": "label",
    "hide_on_screen": "",
    "active": 1,
    "description": "",
    "modified": 1533773495
}